board_game_recommender/__init__.py
board_game_recommender/abc.py
board_game_recommender/baseline.py
board_game_recommender/light.py
board_game_recommender/py.typed
board_game_recommender-4.0.0.dist-info/LICENSE
board_game_recommender-4.0.0.dist-info/METADATA
board_game_recommender-4.0.0.dist-info/WHEEL
board_game_recommender-4.0.0.dist-info/RECORD
