Metadata-Version: 2.1
Name: board-game-recommender
Version: 4.0.0
Summary: Board game recommendation engine
Home-page: https://recommend-games.github.io/board-game-recommender
License: MIT
Author: Markus Shepherd
Author-email: markus@recommend.games
Requires-Python: >=3.9.0,<4.0
Classifier: Development Status :: 4 - Beta
Classifier: Intended Audience :: Developers
Classifier: License :: OSI Approved :: MIT License
Classifier: Operating System :: OS Independent
Classifier: Programming Language :: Python
Classifier: Programming Language :: Python :: 3
Classifier: Programming Language :: Python :: 3.9
Classifier: Programming Language :: Python :: 3.10
Classifier: Programming Language :: Python :: 3.11
Classifier: Programming Language :: Python :: 3.12
Classifier: Programming Language :: Python :: 3.13
Classifier: Topic :: Software Development :: Libraries :: Python Modules
Classifier: Typing :: Typed
Requires-Dist: numpy
Requires-Dist: polars
Project-URL: Documentation, https://recommend-games.github.io/board-game-recommender
Project-URL: Repository, https://github.com/recommend-games/board-game-recommender
